promsoft_cdek_interface/__init__.py
promsoft_cdek_interface/models.py
promsoft_cdek_interface-0.1.3.dist-info/METADATA
promsoft_cdek_interface-0.1.3.dist-info/WHEEL
promsoft_cdek_interface-0.1.3.dist-info/RECORD
