Metadata-Version: 2.1
Name: promsoft-cdek-interface
Version: 0.1.3
Summary: An interface for CDEK HTTP API
Author: Your Name
Author-email: you@example.com
Requires-Python: >=3.10,<4.0
Classifier: Programming Language :: Python :: 3
Classifier: Programming Language :: Python :: 3.10
Classifier: Programming Language :: Python :: 3.11
Requires-Dist: pydantic (>=1.10.6,<2.0.0)
